setup.cfg
setup.py
AstroX.egg-info/SOURCES.txt
astrox/__init__.py
astrox/__main__.py
astrox.egg-info/PKG-INFO
astrox.egg-info/SOURCES.txt
astrox.egg-info/dependency_links.txt
astrox.egg-info/entry_points.txt
astrox.egg-info/pbr.json
astrox.egg-info/requires.txt
astrox.egg-info/top_level.txt