Metadata-Version: 1.0
Name: AstroX
Version: 0.1.105
Summary: AstroX Python Server
Home-page: https://github.com/as2388/AstroX
Author: Alexander Simpson
Author-email: as2388@cam.ac.uk
License: UNKNOWN
Keywords: AstroPi,Scratch,ScratchX
Platform: UNKNOWN
